rescupybs/__init__.py
rescupybs/functions.py
rescupybs/plots.py
rescupybs/wrapper.py
rescupybs-0.1.1.4.dist-info/METADATA
rescupybs-0.1.1.4.dist-info/WHEEL
rescupybs-0.1.1.4.dist-info/entry_points.txt
rescupybs-0.1.1.4.dist-info/top_level.txt
rescupybs-0.1.1.4.dist-info/RECORD
