Metadata-Version: 2.1
Name: rescupybs
Version: 0.1.1.4
Summary: Band structure plot and wavefunction export from rescuplus *.json and *.h5 file.
Home-page: https://github.com/lkccrr/rescupybs
Author: kan
Author-email: luo_kan+pypi@outlook.com
License: MIT
Keywords: DFT rescuplus band plot wavefunction
Platform: Unix
Platform: Windows
Classifier: License :: OSI Approved :: MIT License
Classifier: Programming Language :: Python
Classifier: Programming Language :: Python :: 3
Classifier: Programming Language :: Python :: 3 :: Only
Classifier: Programming Language :: Python :: 3.8
Classifier: Programming Language :: Python :: 3.9
Classifier: Programming Language :: Python :: 3.10
Classifier: Programming Language :: Python :: 3.11
Classifier: Programming Language :: Python :: 3.12
Requires-Python: >=3.8
Requires-Dist: numpy >=1.22.0
Requires-Dist: matplotlib >=3.4.0
Requires-Dist: pint >=0.10
